rangeforce.py
Rangeforce-1.1.0.dist-info/LICENSE.md
Rangeforce-1.1.0.dist-info/METADATA
Rangeforce-1.1.0.dist-info/WHEEL
Rangeforce-1.1.0.dist-info/top_level.txt
Rangeforce-1.1.0.dist-info/RECORD
