Metadata-Version: 2.1
Name: Rangeforce
Version: 1.1.0
Summary: Developer-friendly range checks with user-friendly error messages
Home-page: https://github.com/TheMatjaz/Rangeforce
Author: Matjaž Guštin
Author-email: dev@matjaz.it
License: BSD
Keywords: range,domain,limited,validation,user-input,friendly,understandable
Platform: UNKNOWN
Classifier: Development Status :: 5 - Production/Stable
Classifier: Intended Audience :: Developers
Classifier: License :: OSI Approved :: BSD License
Classifier: Topic :: Software Development
Classifier: Programming Language :: Python :: 3
Classifier: Programming Language :: Python :: 3.4
Classifier: Programming Language :: Python :: 3.5
Classifier: Programming Language :: Python :: 3.6
Classifier: Programming Language :: Python :: 3.7
Classifier: Programming Language :: Python :: 3.8
Requires-Python: >=3
